DataReplay/DataReplay_gui.py
DataReplay/__init__.py
DataReplay/config/__init__.py
DataReplay/config/default_bsd_detect_zone.json
DataReplay/config/default_huichuang_dbc.json
DataReplay/config/default_radar_fov.json
DataReplay/config/default_sim_input.json
DataReplay/config/default_veh_static.json
DataReplay/data/__init__.py
DataReplay/data/can_process _class.py
DataReplay/data/can_process.py
DataReplay/qmls/__init__.py
DataReplay/qmls/bsd_show.py
DataReplay/qmls/bsd_show.qml
DataReplay/qmls/content/Dial.qml
DataReplay/qmls/content/__init__.py
DataReplay/qmls/content/background.png
DataReplay/qmls/content/needle.png
DataReplay/qmls/content/needle_shadow.png
DataReplay/qmls/content/overlay.png
DataReplay/ui/__init__.py
DataReplay/ui/cam.ui
DataReplay/ui/cam_ui.py
DataReplay/ui/sim.qrc
DataReplay/ui/sim.ui
DataReplay/ui/sim_rc.py
DataReplay/ui/sim_ui.py
DataReplay/ui/images/__init__.py
DataReplay/ui/images/cycle.png
DataReplay/ui/images/logo.png
DataReplay/ui/images/pause.png
DataReplay/ui/images/play.png
DataReplay/utils/__init__.py
DataReplay/utils/utils.py
DataReplay/widgets/__init__.py
DataReplay/widgets/cam_widget.py
DataReplay/widgets/camera_show.py
DataReplay/widgets/sim_widget.py
DataShow/DataShow_gui.py
DataShow/__init__.py
DataShow/config/__init__.py
DataShow/config/default_bsd_detect_zone.json
DataShow/config/default_huichuang_dbc.json
DataShow/config/default_radar_fov.json
DataShow/config/default_sim_input.json
DataShow/config/default_veh_static.json
DataShow/data/__init__.py
DataShow/data/can_process _class.py
DataShow/data/can_process.py
DataShow/data/uart_process.py
DataShow/qmls/__init__.py
DataShow/qmls/bsd_show.py
DataShow/qmls/bsd_show.qml
DataShow/qmls/content/Dial.qml
DataShow/qmls/content/__init__.py
DataShow/qmls/content/background.png
DataShow/qmls/content/needle.png
DataShow/qmls/content/needle_shadow.png
DataShow/qmls/content/overlay.png
DataShow/ui/__init__.py
DataShow/ui/cam.ui
DataShow/ui/cam_ui.py
DataShow/ui/sim.qrc
DataShow/ui/sim.ui
DataShow-6.10.1.dist-info/METADATA
DataShow-6.10.1.dist-info/WHEEL
DataShow-6.10.1.dist-info/entry_points.txt
DataShow-6.10.1.dist-info/top_level.txt
DataShow-6.10.1.dist-info/RECORD
