Metadata-Version: 2.1
Name: DataShow
Version: 6.10.1
Summary: a tool for showing radar info
Home-page: UNKNOWN
Author: Andy.Yang
Author-email: andy.yang@deftech.com
License: UNKNOWN
Platform: UNKNOWN
Classifier: Programming Language :: Python :: 3.7
Classifier: Programming Language :: Python :: 3.8
Classifier: Operating System :: Microsoft :: Windows :: Windows 10
Requires-Python: >=3.7.0
Requires-Dist: wheel
Requires-Dist: numpy
Requires-Dist: PyQt5
Requires-Dist: PyQtChart
Requires-Dist: opencv-python
Requires-Dist: PyQt5-sip
Requires-Dist: pyqtgraph
Requires-Dist: python-can
Requires-Dist: scipy
Requires-Dist: python-dateutil
Requires-Dist: pytz
Requires-Dist: windows-curses
Requires-Dist: wrapt
Requires-Dist: pandas
Requires-Dist: six
Requires-Dist: pyserial
